CHANGES.rst
LICENSE
MANIFEST.in
README.rst
setup.py
pytest_play/__init__.py
pytest_play/config.py
pytest_play/engine.py
pytest_play/plugin.py
pytest_play.egg-info/PKG-INFO
pytest_play.egg-info/SOURCES.txt
pytest_play.egg-info/dependency_links.txt
pytest_play.egg-info/entry_points.txt
pytest_play.egg-info/not-zip-safe
pytest_play.egg-info/requires.txt
pytest_play.egg-info/top_level.txt
pytest_play/providers/__init__.py
pytest_play/providers/base.py
pytest_play/providers/include.py
pytest_play/providers/metrics.py
pytest_play/providers/python.py