Metadata-Version: 2.1
Name: pytest-play
Version: 2.3.0
Summary: pytest plugin that let you automate actions and assertions with test metrics reporting executing plain YAML files
Home-page: https://github.com/davidemoro/pytest-play
Author: Davide Moro
Author-email: davide.moro@gmail.com
Maintainer: Davide Moro
Maintainer-email: davide.moro@gmail.com
License: Apache Software License 2.0
Platform: UNKNOWN
Classifier: Development Status :: 5 - Production/Stable
Classifier: Framework :: Pytest
Classifier: Intended Audience :: Developers
Classifier: Topic :: Software Development :: Testing
Classifier: Programming Language :: Python
Classifier: Programming Language :: Python :: 3
Classifier: Programming Language :: Python :: 3.6
Classifier: Programming Language :: Python :: 3.7
Classifier: Programming Language :: Python :: Implementation :: CPython
Classifier: Operating System :: OS Independent
Classifier: License :: OSI Approved :: Apache Software License
Provides-Extra: statsd
Provides-Extra: tests
Provides-Extra: docs
